scdil/__init__.py
scdil/_ast.py
scdil/_dump.py
scdil/_frozendict.py
scdil/_frozenlist.py
scdil/_load.py
scdil/_parse.py
scdil/_types.py
scdil/_version.py
scdil/py.typed
scdil-0.1.dist-info/LICENSE
scdil-0.1.dist-info/METADATA
scdil-0.1.dist-info/WHEEL
scdil-0.1.dist-info/top_level.txt
scdil-0.1.dist-info/RECORD
