Metadata-Version: 2.1
Name: scdil
Version: 0.1
Summary: simple configuration and data interchange language
Home-page: https://github.com/ktbarrett/scdil
Author: Kaleb Barrett
Author-email: dev.ktbarrett@gmail.com
License: MIT
Classifier: Development Status :: 2 - Pre-Alpha
Classifier: Intended Audience :: Developers
Classifier: License :: OSI Approved :: MIT License
Classifier: Programming Language :: Python :: 3
Requires-Python: >=3.7, <4
License-File: LICENSE
